gitsweep/__init__.py
gitsweep/base.py
gitsweep/cli.py
gitsweep/deleter.py
gitsweep/entrypoints.py
gitsweep/inspector.py
gitsweep/scripts/__init__.py
gitsweep/scripts/test.py
gitsweep/tests/__init__.py
gitsweep/tests/test_cli.py
gitsweep/tests/test_deleter.py
gitsweep/tests/test_inspector.py
gitsweep/tests/testcases.py
git_sweep3-0.2.0.dist-info/entry_points.txt
git_sweep3-0.2.0.dist-info/LICENSE.txt
git_sweep3-0.2.0.dist-info/WHEEL
git_sweep3-0.2.0.dist-info/METADATA
git_sweep3-0.2.0.dist-info/RECORD
