Metadata-Version: 2.1
Name: git-sweep3
Version: 0.2.0
Summary: Clean up branches from your Git remotes
Home-page: https://github.com/talhajunaidd/git-sweep3
License: MIT
Keywords: git,maintenance,branches
Author: Talha Junaid
Author-email: talhajunaidd@gmail.com
Requires-Python: >=3.7,<3.10.0
Classifier: Development Status :: 4 - Beta
Classifier: Environment :: Console
Classifier: Intended Audience :: Developers
Classifier: License :: OSI Approved :: MIT License
Classifier: Natural Language :: English
Classifier: Operating System :: POSIX
Classifier: Programming Language :: Python :: 3
Classifier: Programming Language :: Python :: 3.7
Classifier: Programming Language :: Python :: 3.8
Classifier: Programming Language :: Python :: 3.9
Classifier: Programming Language :: Python :: 3.7
Classifier: Programming Language :: Python :: 3.8
Classifier: Programming Language :: Python :: 3.9
Classifier: Topic :: Software Development :: Quality Assurance
Classifier: Topic :: Software Development :: Version Control
Classifier: Topic :: Text Processing
Requires-Dist: GitPython (>=3.1.24,<4.0.0)
Project-URL: Repository, https://github.com/talhajunaidd/git-sweep3
